odoo9_addon_pos_customer_display-9.0.0.1.0-py2.7-nspkg.pth
odoo9_addon_pos_customer_display-9.0.0.1.0.dist-info/top_level.txt
odoo9_addon_pos_customer_display-9.0.0.1.0.dist-info/WHEEL
odoo9_addon_pos_customer_display-9.0.0.1.0.dist-info/RECORD
odoo9_addon_pos_customer_display-9.0.0.1.0.dist-info/metadata.json
odoo9_addon_pos_customer_display-9.0.0.1.0.dist-info/DESCRIPTION.rst
odoo9_addon_pos_customer_display-9.0.0.1.0.dist-info/METADATA
odoo9_addon_pos_customer_display-9.0.0.1.0.dist-info/namespace_packages.txt
odoo_addons/pos_customer_display/pos_customer_display.py
odoo_addons/pos_customer_display/__openerp__.py
odoo_addons/pos_customer_display/pos_customer_display_demo.xml
odoo_addons/pos_customer_display/__init__.py
odoo_addons/pos_customer_display/i18n/es.po
odoo_addons/pos_customer_display/i18n/pos_customer_display.pot
odoo_addons/pos_customer_display/i18n/nl.po
odoo_addons/pos_customer_display/i18n/de.po
odoo_addons/pos_customer_display/i18n/fr.po
odoo_addons/pos_customer_display/views/customer_display_view.xml
odoo_addons/pos_customer_display/views/pos_customer_display.xml
odoo_addons/pos_customer_display/static/src/js/customer_display.js
odoo_addons/pos_customer_display/static/src/css/pos_customer_display.css
odoo_addons/pos_customer_display/static/src/xml/pos.xml
